setup.cfg
setup.py
polukrug/__init__.py
polukrug.egg-info/PKG-INFO
polukrug.egg-info/SOURCES.txt
polukrug.egg-info/dependency_links.txt
polukrug.egg-info/not-zip-safe
polukrug.egg-info/top_level.txt