Metadata-Version: 1.0
Name: polukrug
Version: 1.0
Summary: Нарисуй полукруг!
Home-page: UNKNOWN
Author: UNKNOWN
Author-email: p.dergalin@sch-int.ru
License: UNKNOWN
Platform: UNKNOWN
